pyoutreg/__init__.py
pyoutreg/outreg.py
pyoutreg/core/__init__.py
pyoutreg/core/formatter.py
pyoutreg/core/options.py
pyoutreg/core/regression_parser.py
pyoutreg/exporters/__init__.py
pyoutreg/exporters/docx_exporter.py
pyoutreg/exporters/xlsx_exporter.py
pyoutreg/utils/__init__.py
pyoutreg/utils/helpers.py
pyoutreg/utils/statistics.py
pyoutreg-0.1.1.dist-info/licenses/LICENSE
pyoutreg-0.1.1.dist-info/METADATA
pyoutreg-0.1.1.dist-info/WHEEL
pyoutreg-0.1.1.dist-info/top_level.txt
pyoutreg-0.1.1.dist-info/RECORD
