Metadata-Version: 2.4
Name: pyoutreg
Version: 0.1.1
Summary: A Python implementation of Stata's outreg2 for exporting regression results
Author-email: Bryce Wang <brycew6m@stanford.edu>
Maintainer-email: Bryce Wang <brycew6m@stanford.edu>
License-Expression: MIT
Project-URL: Homepage, https://github.com/brycewang-stanford/pyoutreg
Project-URL: Repository, https://github.com/brycewang-stanford/pyoutreg
Project-URL: Documentation, https://github.com/brycewang-stanford/pyoutreg/blob/main/README.md
Project-URL: Changelog, https://github.com/brycewang-stanford/pyoutreg/blob/main/CHANGELOG.md
Project-URL: Bug Tracker, https://github.com/brycewang-stanford/pyoutreg/issues
Keywords: regression,statistics,stata,econometrics,export,excel,word,tables,outreg
Classifier: Development Status :: 3 - Alpha
Classifier: Intended Audience :: Science/Research
Classifier: Operating System :: OS Independent
Classifier: Programming Language :: Python :: 3
Classifier: Programming Language :: Python :: 3.7
Classifier: Programming Language :: Python :: 3.8
Classifier: Programming Language :: Python :: 3.9
Classifier: Programming Language :: Python :: 3.10
Classifier: Programming Language :: Python :: 3.11
Classifier: Programming Language :: Python :: 3.12
Classifier: Programming Language :: Python :: 3.13
Classifier: Topic :: Scientific/Engineering
Classifier: Topic :: Office/Business :: Office Suites
Requires-Python: >=3.7
License-File: LICENSE
Requires-Dist: pandas>=1.3.0
Requires-Dist: numpy>=1.20.0
Requires-Dist: statsmodels>=0.12.0
Requires-Dist: linearmodels>=4.25
Requires-Dist: openpyxl>=3.0.0
Requires-Dist: python-docx>=0.8.11
Requires-Dist: scipy>=1.7.0
Provides-Extra: dev
Requires-Dist: pytest>=6.0; extra == "dev"
Requires-Dist: pytest-cov>=2.0; extra == "dev"
Requires-Dist: black>=21.0; extra == "dev"
Requires-Dist: flake8>=3.8; extra == "dev"
Requires-Dist: mypy>=0.800; extra == "dev"
Provides-Extra: test
Requires-Dist: pytest>=6.0; extra == "test"
Requires-Dist: pytest-cov>=2.0; extra == "test"
Provides-Extra: docs
Requires-Dist: sphinx>=4.0; extra == "docs"
Requires-Dist: sphinx-rtd-theme>=1.0; extra == "docs"
Requires-Dist: nbsphinx>=0.8; extra == "docs"
Dynamic: license-file
